pyCHX/Badpixels.py
pyCHX/Compress_readerNew.py
pyCHX/Create_Report.py
pyCHX/DEVs.py
pyCHX/DataGonio.py
pyCHX/SAXS.py
pyCHX/Stitching.py
pyCHX/Two_Time_Correlation_Function.py
pyCHX/XPCS_GiSAXS.py
pyCHX/XPCS_SAXS.py
pyCHX/XPCS_XSVS_SAXS_Multi_2017_V4.py
pyCHX/__init__.py
pyCHX/_version.py
pyCHX/chx_Fitters2D.py
pyCHX/chx_compress.py
pyCHX/chx_compress_analysis.py
pyCHX/chx_correlation.py
pyCHX/chx_correlationc.py
pyCHX/chx_correlationp.py
pyCHX/chx_correlationp2.py
pyCHX/chx_crosscor.py
pyCHX/chx_generic_functions.py
pyCHX/chx_handlers.py
pyCHX/chx_libs.py
pyCHX/chx_olog.py
pyCHX/chx_outlier_detection.py
pyCHX/chx_packages.py
pyCHX/chx_speckle.py
pyCHX/chx_specklecp.py
pyCHX/chx_xpcs_xsvs_jupyter_V1.py
pyCHX/movie_maker.py
pyCHX/xpcs_timepixel.py
pyCHX/tests/__init__.py
pyCHX/tests/conftest.py
pyCHX/tests/test_examples.py
pyCHX/v2/__init__.py
pyCHX/v2/_commonspeckle/DEVs.py
pyCHX/v2/_commonspeckle/DataGonio.py
pyCHX/v2/_commonspeckle/SAXS.py
pyCHX/v2/_commonspeckle/Stitching.py
pyCHX/v2/_commonspeckle/Two_Time_Correlation_Function.py
pyCHX/v2/_commonspeckle/XPCS_GiSAXS.py
pyCHX/v2/_commonspeckle/XPCS_SAXS.py
pyCHX/v2/_commonspeckle/XPCS_XSVS_SAXS_Multi_2017_V4.py
pyCHX/v2/_commonspeckle/__init__.py
pyCHX/v2/_commonspeckle/chx_Fitters2D.py
pyCHX/v2/_commonspeckle/chx_compress.py
pyCHX/v2/_commonspeckle/chx_compress_analysis.py
pyCHX/v2/_commonspeckle/chx_correlation.py
pyCHX/v2/_commonspeckle/chx_correlationc.py
pyCHX/v2/_commonspeckle/chx_correlationp.py
pyCHX/v2/_commonspeckle/chx_correlationp2.py
pyCHX/v2/_commonspeckle/chx_generic_functions.py
pyCHX/v2/_commonspeckle/chx_handlers.py
pyCHX/v2/_commonspeckle/chx_libs.py
pyCHX/v2/_commonspeckle/chx_olog.py
pyCHX/v2/_commonspeckle/chx_speckle.py
pyCHX/v2/_commonspeckle/chx_specklecp.py
pyCHX/v2/_commonspeckle/chx_xpcs_xsvs_jupyter_V1.py
pyCHX/v2/_commonspeckle/movie_maker.py
pyCHX/v2/_commonspeckle/xpcs_timepixel.py
pyCHX/v2/_futurepyCHX/Badpixels.py
pyCHX/v2/_futurepyCHX/Compress_readerNew.py
pyCHX-4.3.1.dist-info/AUTHORS.rst
pyCHX-4.3.1.dist-info/LICENSE
pyCHX-4.3.1.dist-info/METADATA
pyCHX-4.3.1.dist-info/WHEEL
pyCHX-4.3.1.dist-info/top_level.txt
pyCHX-4.3.1.dist-info/RECORD
