Metadata-Version: 2.1
Name: pyCHX
Version: 4.3.1
Summary: pyCHX - CHX XPCS Data Analysis Package
Home-page: https://github.com/NSLS-II/pyCHX
Author: Brookhaven National Laboratory CHX
License: BSD-3-Clause
Classifier: Development Status :: 2 - Pre-Alpha
Classifier: Natural Language :: English
Classifier: Programming Language :: Python :: 3
Requires-Python: >=3.6
License-File: LICENSE
License-File: AUTHORS.rst
Requires-Dist: cython
Requires-Dist: dask
Requires-Dist: databroker
Requires-Dist: dill
Requires-Dist: historydict
Requires-Dist: ipython
Requires-Dist: lmfit
Requires-Dist: matplotlib
Requires-Dist: numpy
Requires-Dist: pandas
Requires-Dist: pillow
Requires-Dist: pyyaml
Requires-Dist: reportlab
Requires-Dist: scikit-image
Requires-Dist: scipy
Requires-Dist: theano
Requires-Dist: tifffile
Requires-Dist: tqdm
